{"animated": ["cartoon", "plane"], "inflatable": ["crocodile", "swimming", "float"], "difficulty": ["across", "four"], "high": ["top"], "singer": ["man", "on"], "pianist": ["man"], "bounce": ["lie", "play"], "healthy": ["malnourished"], "hand": ["hat", "throw", "pavement", "shirt", "towards", "sunglass", "man"], "rescue": ["raft"], "tongue": ["mouth", "dog"], "match": ["kickboxing"], "sad": ["man", "happy"], "blond": ["lady", "white", "child", "girl"], "sausage": ["season", "seasoning"], "past": ["player", "with", "in"], "stir": ["mix", "boil", "beat"], "two": ["at", "biker", "for", "different", "large", "small", "child", "sit", "egg", "four", "newspaper", "on", "cat", "man", "into", "big", "fist", "three", "dog", "white", "eggs", "golden", "woman", "provide"], "parking": ["street", "sidewalk"], "piercing": ["girl"], "challengingly": ["dance"], "staircase": ["step"], "swimming": ["inflatable", "bikini", "fish", "dog", "swimsuit", "dune", "suit", "pool"], "rope": ["toy", "cord", "bridge", "mountain"], "crowd": ["paint", "large", "down", "front", "with"], "tiredly": ["tire", "run", "slowly", "sit"], "sheep": ["llama"], "interior": ["colorful"], "extravagant": ["dress"], "tiger": ["baby"], "sauce": ["milk", "man"], "biking": ["mountain"], "practice": ["white", "fight", "kick", "range", "require", "play"], "pass": ["jump"], "give": ["talk"], "around": ["roar", "in", "sound", "sit", "slowly", "look", "make", "outside", "adult", "lean", "walk", "down"], "point": ["look"], "snowy": ["rain", "muddy"], "Rel": ["makeup"], "(_box": ["box"], "about": ["on"], "quickly": ["fast", "eat", "chase", "jump", "run", "chop", "slice", "cross"], "sunny": ["day", "bunch", "snow", "man", "rainy", "orange"], "area": ["walk", "sweater", "through", "wood", "man", "sand", "outdoor", "large", "hike"], "whack": ["spank"], "motionlessly": ["pose"], "heal": ["revive"], "stuntman": ["man"], "retrieve": ["hold"], "follow": ["shun", "walk"], "lamp": ["pole", "boy"], "veil": ["dress"], "eyelid": ["eyeshadow"], "bikini": ["on", "swimming"], "chef": ["woman", "man"], "far": ["swiftly"], "walk": ["watch", "follow", "lie", "wear", "beach", "roar", "stop", "dance", "stand", "sit", "look", "colorful", "chase", "restrain", "lick", "swim", "take", "rest"], "famous": ["on", "man"], "panda": ["cub"], "helmet": ["bicycle", "race"], "volleyball": ["frisbee"], "comb": ["arrange", "brush", "ruffle"], "walking": ["standing"], "dress": ["black", "veil", "elegant"], "restrain": ["walk"], "ping": ["tennis"], "church": ["child"], "violently": ["strike"], "beautiful": ["flow", "waterfall", "thick"], "enjoy": ["on"], "skillfully": ["sing", "break", "play"], "swamp": ["water"], "hot": ["sunny"], "hit": ["squirt"], "metallic": ["wooden"], "design": ["motocross"], "casual": ["shirt", "uniform"], "t-ball": ["ball", "baseball", "little"], "cowboy": ["blue", "through", "hat"], "cartoon": ["animated", "plane"], "yellow": ["wheel", "tan", "golden", "two", "toy", "flower", "race", "green", "ride", "dog"], "skateboard": ["bike"], "scout": ["explorer"], "discussion": ["laughing"], "calmly": ["flow"], "paint": ["in", "with", "bike"], "peacefully": ["wear", "lie", "tree", "sit", "sunset"], "rainbow": ["colorful"], "brush": ["crouch", "comb", "wash", "scrub", "style"], "rest": ["race", "walk", "play", "lounge", "catch", "jump", "tap", "run"], "grey": ["dog"], "flip": ["compete", "jump"], "out": ["outside", "pour", "run", "push", "boil", "squeeze", "jump", "young", "mouth", "bite", "carry", "into", "roll", "play", "walk", "look", "flow"], "land": ["ride", "cling"], "elderly": ["woman", "elder", "lady"], "sniff": ["stand"], "experience": ["asleep"], "violin": ["piano", "harp", "on"], "bare-chested": ["wear"], "sprinkle": ["put", "remove"], "silky": ["black"], "blonde": ["bald", "woman"], "break": ["mix", "stand", "relax"], "style": ["brush", "mess"], "jar": ["can"], "subject": ["camera"], "grassy": ["sweater", "side", "field"], "stand": ["wade", "smile", "man", "swim", "look", "hang", "dog", "walk", "sound", "lean", "hold", "wear", "do", "jump", "climb", "run", "play", "dance", "sing", "wait"], "number": ["ear"], "girl": ["four", "horse", "man", "dancer", "lady", "bride", "red", "skateboarder", "on"], "dye": ["huge", "die", "purple"], "wet": ["beach"], "family": ["boy"], "motocross": ["motorbike", "bike", "jacket", "gear"], "cooking": ["okra", "man", "stove", "pot", "oil", "woman"], "beige": ["tan"], "over": ["on", "leap", "obstacle", "with", "up", "into", "under", "inside", "cover", "lone"], "((_ball": ["dog"], "amusedly": ["watch", "stand"], "pocket": ["hat"], "toddle": ["crawl"], "deep": ["woman"], "age": ["teenage"], "absently": ["eat", "cut"], "funnily": ["play", "grab", "attentively"], "onion": ["ginger", "carrot", "garlic", "meat", "potato", "tofu"], "young": ["toddler", "woman", "boy", "topless", "man", "child", "bicyclist", "kid", "jump", "girl", "out", "two", "brown"], "escort": ["lead"], "hillside": ["hill"], "phone": ["toy"], "throw": ["peel", "hand", "do", "extract", "check"], "eating": ["man"], "rocky": ["hike", "walk", "low", "pebbly", "river"], "way": ["play"], "camera": ["photo", "on", "picture", "photograph", "photographer", "underwater"], "hole": ["earth"], "gather": ["mask", "scatter", "stand", "run"], "cute": ["bear"], "ride": ["dive", "seat", "dyed", "get", "lean", "wear", "off", "stop", "surf", "kayake"], "swimmer": ["boy"], "white": ["different", "onion", "two", "look", "with", "large", "cat", "into", "the", "little", "dress", "brown", "ice", "tan", "sheep", "snow", "wheel", "hand", "bench", "red", "dog"], "child": ["wheelie", "animal", "wooden"], "midspeech": ["with"], "microphone": ["singing"], "eat": ["peel", "play", "hungry", "cut", "puke", "sleep", "talk", "remove", "slice", "cut", "fast", "scrub", "silent"], "courageously": ["do"], "toss": ["launch"], "graphitize": ["graffitus"], "greedily": ["eagerly", "drink"], "shirtless": ["little", "man", "wear", "ride", "woman", "small"], "sugar": ["spice"], "spoon": ["pot"], "contain": ["open"], "steel": ["rope"], "by": ["bunch", "banana"], "fresh": ["milk"], "building": ["striped", "fountain", "shop"], "store": ["wear", "market", "chop"], "arrange": ["comb"], "soldier": ["military", "recruit"], "desert": ["ride", "wooded", "wood"], "european": ["american"], "kneel": ["pose"], "raw": ["crack"], "leap": ["play"], "seat": ["ride", "car", "man"], "shore": ["sand", "bicycle", "beach"], "earth": ["hole"], "perch": ["perform", "fly", "ride"], "trainer": ["protective"], "chair": ["couch"], "snowboarder": ["board"], "listlessly": ["sit"], "carelessly": ["empty"], "tail": ["climb"], "toe": ["with", "boot"], "tire": ["tiredly"], "bark": ["listen"], "make": ["participate", "whisk", "whisk", "talk", "hang", "splash", "crack", "empty", "around", "climb", "speak", "open", "jump"], "table": ["perch", "equipment", "with", "tap", "sit", "pong", "cabinet", "restaurant"], "ramp": ["bmx", "biker", "bike"], "car": ["bike", "bicycle", "horse"], "gray": ["run", "colorful", "suit", "front", "elderly"], "tube": ["tunnel"], "bell": ["orange"], "tool": ["pole"], "ball": ["child", "t-ball", "play", "man", "boy", "base", "doll", "player"], "paddling": ["kiddie"], "pot": ["pan", "boil", "bowl"], "many": ["lot", "large", "cheerleader", "woman"], "heartily": ["sing"], "nervously": ["tap"], "knee": ["green", "cheerleader", "kid"], "container": ["faucet"], "market": ["store"], "colorful": ["interior", "bird", "gray", "rainbow", "birdcage", "building", "blue"], "handle": ["aim"], "talk": ["walk", "with", "ignore", "travel", "crack", "listen", "phone", "say", "play"], "pencil": ["knife", "write"], "american": ["european", "player"], "use": ["open", "hold", "whisk", "equip", "sew", "leave", "communicate", "whisk"], "muzzle": ["uniform", "blanket"], "slice": ["put", "pick"], "adult": ["couple"], "jacket": ["still", "man", "sit", "woman", "blue", "pink", "blanket", "cloth"], "hungrily": ["lick", "eating", "give"], "brown": ["grassy", "boy", "dog", "chair", "golden", "young", "bird", "corner", "area", "white"], "fit": ["apply"], "basement": ["tambourine"], "obstacle": ["railing"], "base": ["waterfall"], "clown": ["orange"], "baseball": ["t-ball"], "ingredient": ["vegetable", "egg", "into"], "tank": ["in", "speak"], "fiercely": ["flap", "point"], "student": ["classroom"], "mountain": ["rock", "hillside", "wall", "bicycle", "hill", "beach", "dusk", "mountainside"], "scold": ["play"], "swim": ["sit", "walk", "stand", "immobile"], "font": ["front"], "foamy": ["wave"], "tear": ["cut"], "lap": ["train"], "orange": ["pepper", "pink", "make", "black"], "bmx": ["bike", "uniform", "biker"], "shades": ["soda", "hair"], "wagon": ["corndog"], "leotard": ["blue"], "practitioner": ["man"], "dune": ["suite", "bikini"], "tattoo": ["drawing"], "(_ball": ["dog"], "dangerous": ["man"], "front": ["building", "rock", "car", "woman", "white", "camera", "parrot", "room", "forest", "can", "brown", "gray", "dress", "green", "fountain", "wooden", "font", "water", "wall", "paint", "shirt"], "lose": ["chase"], "color": ["ride"], "woman": ["on", "dance", "tomato", "animal", "old", "boil", "into", "strong", "dim", "cleanse", "food", "bride", "stand", "dog", "four", "motorcyclist", "strongly", "player", "couple", "singing", "two", "sing", "child", "chef", "bicyclist", "cook", "boy", "water", "zucchini"], "edge": ["dusk", "beach"], "harp": ["guitar", "violin"], "wall": ["building", "woman", "ground", "mountain", "climb"], "purple": ["guitar", "climb", "player", "large", "uniform"], "lean": ["stand", "play", "around", "man", "turn", "look", "wear"], "outside": ["curiously", "out", "front", "run", "rope", "lead", "lie", "dance", "in", "around", "down", "sit", "tennis", "walk", "ball", "soccer", "hold", "move", "up", "smile", "remove", "stand"], "muscular": ["shirtless"], "juice": ["lemon"], "elegant": ["woman"], "golden": ["yellow", "brown", "two"], "pole": ["wooden", "post"], "shred": ["study"], "cautiously": ["type", "feed"], "wakeboard": ["waterskie"], "path": ["road", "dirt"], "grass": ["field", "water", "lawn", "dog", "green", "mouth", "orange", "brown", "three", "walk", "backyard", "back", "sand", "chasing"], "eagerly": ["greedily"], "beside": ["man", "automobile", "bird", "stand", "up"], "keyboard": ["instrument", "guitar", "harp", "piano", "cat", "flute"], "courageous": ["man"], "sandy": ["pebbly", "dirt", "ride", "beach"], "off": ["point", "jump", "hold", "ride", "get", "fly", "climb", "into", "swiftly"], "riskily": ["jump"], "difficultly": ["walk", "run"], "arm": ["hair", "kangaroo", "cheer", "green", "girl"], "another": ["tree", "object"], "sew": ["unstitch"], "scarf": ["afghan"], "lone": ["man", "bicyclist"], "steadily": ["sit", "stand"], "blanket": ["blue", "jacket"], "gym": ["field", "park"], "spice": ["sugar"], "doll": ["ball"], "recruit": ["soldier"], "do": ["ride", "dance", "flip", "stop", "throw", "only", "on", "dance", "spar", "from", "stand", "jump", "skateboard"], "sing": ["dance", "sit"], "performer": ["man"], "play": ["still", "middle", "pet", "away", "dance", "look", "pack", "sleep", "chase", "push", "lie", "snap", "splash", "drop", "fight", "lick", "sit", "scold", "hold", "eat", "jump", "fall", "rest", "stand", "climb", "stare", "practice", "study", "read", "strum", "talk"], "leave": ["play", "chase", "perform"], "muddy": ["rugby", "snowy"], "spread": ["butter", "remove", "wipe", "girl"], "hug": ["fight", "white"], "back": ["leap", "mouth", "jump", "flip", "belly"], "sticky": ["pasta"], "brick": ["red"], "jetskus": ["seadoo"], "behind": ["next"], "new": ["blue"], "chimp": ["monkey"], "uninterestedly": ["stand"], "aim": ["draw", "handle"], "costumed": ["clown"], "red": ["car", "black", "leaf", "corner", "tuxedo", "brown", "onion", "race", "ground", "air", "fish", "blue", "dress", "man", "race", "kid", "darkened", "dog"], "sky": ["star", "fly"], "rugby": ["soccer"], "lazily": ["walk"], "llama": ["sheep"], "tirelessly": ["play"], "during": ["in"], "crazily": ["around"], "bowl": ["pot", "butter", "cereal"], "bearded": ["man"], "roof": ["top"], "sea": ["turtle", "beach"], "big": ["on", "into", "fish", "bowl", "wave", "dog", "cat", "blue", "garlic"], "hiker": ["man"], "playfully": ["smile", "frolic", "cat", "swim"], "swimsuit": ["swimming"], "telephonic": ["phone"], "sneeze": ["sit", "cheer"], "acoustic": ["guitar"], "shrewd": ["shrewdly", "burrow"], "hike": ["next", "trek", "with"], "shoot": ["reload"], "blonds": ["lady"], "frolic": ["run", "sit"], "forest": ["tree", "costume", "snow", "rain"], "dusk": ["edge"], "skateboarder": ["man"], "naked": ["dance", "down", "wear", "girl", "lie"], "patient": ["man"], "maraca": ["tambourine"], "into": ["over", "ingredient", "potato", "butter", "from", "for", "in", "slice", "at", "onto", "on", "of", "dice", "goal", "through", "boil", "bite", "up", "off", "with"], "shop": ["building"], "speedily": ["ride"], "onstage": ["stage"], "cloth": ["jacket"], "disassemble": ["play"], "nicely": ["walk", "man"], "goggles": ["gear"], "strip": ["sport"], "hooded": ["red"], "dangerously": ["jump", "dance", "do", "motorcyclist", "dangerous"], "through": ["south", "across", "into", "of", "out", "in", "two", "motorbike", "walk", "near", "on", "motorcycle", "child", "rough", "dog", "woman"], "carry": ["bite", "drop", "walk"], "karate": ["man"], "dry": ["leaf"], "board": ["over", "tile"], "living": ["park"], "a": ["man", "large"], "ship": ["boat"], "cluster": ["four"], "player": ["woman", "game", "ball", "tennis", "man"], "folded": ["black"], "listen": ["ignore", "bark", "talk", "attentively"], "stage": ["play", "podium", "onstage", "dance", "stand"], "pedestrians": ["crowded"], "ice": ["hockey"], "curiously": ["look", "outside"], "river": ["marsh"], "father": ["man"], "refrigerate": ["peel"], "little": ["white", "one", "kitten", "laugh", "girl", "table", "walk", "up", "shiny", "child", "boy", "into"], "rise": ["wear"], "teens": ["man", "teenage"], "cane": ["bamboo"], "silver": ["pink", "wear", "bicycle"], "fireplace": ["mantel"], "proudly": ["run"], "happy": ["family"], "female": ["cheerleader"], "leafless": ["tree"], "free": ["catch"], "voraciously": ["eat"], "to": ["mouse", "at", "pole"], "sweater": ["grassy"], "pour": ["prepare", "put", "out", "season", "remove"], "divinely": ["dance"], "different": ["white", "two", "costume", "dog"], "drawing": ["tattoo", "work"], "machine": ["man", "pencil"], "joyfully": ["cheerfully", "run"], "look": ["hold", "walk", "stand", "lounge", "sniff", "watch", "roll", "sit", "brown", "play", "wade", "pose", "climb", "investigate", "swim", "sleep", "study", "lean"], "middle": ["kid", "man", "gym"], "place": ["crack", "cook", "boil"], "take": ["crack", "dance", "sit", "airborne", "wear", "fly", "relax", "push", "pour", "boil"], "lawn": ["chair", "garden", "road", "grass"], "vicinity": ["forest"], "next": ["stand", "sit", "rest", "wear", "pose", "climb", "up", "behind", "hang", "keep", "show", "wait"], "lay": ["roll"], "very": ["funny", "huge", "white", "day", "near"], "motorcyclist": ["woman", "man"], "kayak": ["kayake"], "pet": ["brown", "dog"], "chap": ["man"], "dish": ["milk"], "sleeved": ["blue"], "tap": ["rest"], "floor": ["two", "court", "exercise", "ceiling", "off", "pig", "devour"], "not": ["play"], "pasture": ["cattle"], "egyptian": ["indian", "headdress", "black"], "float": ["crocodile", "push", "inflatable"], "grab": ["scramble", "stare"], "lounge": ["rest"], "without": ["with"], "snow": ["rain", "snowboard", "outdoors", "in"], "flag": ["front"], "pedestrian": ["woman"], "pebbly": ["sandy", "rocky", "beach"], "(_man": ["man"], "turn": ["push", "chase"], "candle": ["dim"], "logo": ["motocross"], "wrestler": ["ringer"], "sidewalk": ["seashore", "road", "girl", "street", "curb"], "chop": ["put", "store", "dice"], "drive": ["outside"], "bike": ["car", "gear", "white", "skateboard", "biker", "knife", "bmx"], "sadly": ["frolic"], "green": ["front", "bag", "crocodile", "golden", "white", "ride", "black", "blue", "pool", "grass", "bike", "into", "pepper", "bent", "inflatable", "pepper", "on", "field"], "belly": ["lemur", "back"], "abruptly": ["off"], "garage": ["sidewalk", "car", "street"], "pong": ["tennis"], "ignore": ["talk", "listen"], "wash": ["brush"], "face": ["wear", "mask", "black", "makeup"], "boil": ["stir", "dry"], "black": ["blue", "cat", "dog", "bucket", "bench", "kid", "bite", "bikini", "little", "wheel", "two", "hand", "biker", "cloak", "look", "large"], "racer": ["motocross", "man"], "beautifully": ["dance"], "alongside": ["outside"], "deny": ["pose"], "creek": ["man", "ride"], "horse": ["motorcycle", "dog"], "prepare": ["discard", "carefully", "clean"], "cling": ["land"], "lens": ["camera"], "angrily": ["look"], "sun": ["sand", "on"], "target": ["wear", "tree", "range"], "fail": ["do"], "snowsuit": ["snow"], "recklessly": ["climb", "jump"], "noisily": ["bark"], "drop": ["run", "carry", "stare", "up", "play", "hold", "bite"], "stupidly": ["throw"], "chase": ["have", "run"], "hurriedly": ["get"], "manicure": ["hair"], "jumper": ["swimmer", "biker"], "rally": ["racing"], "ringer": ["wrestler"], "egg": ["mixture", "cook", "ingredient", "meat"], "coat": ["grate", "cat", "white"], "explorer": ["scout"], "photographer": ["man"], "sharpen": ["shave"], "pick": ["slice", "plant", "drop"], "african": ["airplane"], "podium": ["stage"], "old": ["motorcycle", "man", "microphone", "sit", "woman"], "powerfully": ["perform"], "cardboard": ["box", "money"], "boy": ["toddler", "guy", "biker", "woman", "young", "play", "baby", "lady"], "four": ["young", "atv", "two", "on", "kid"], "pants": ["sit", "man"], "winter": ["weather"], "direction": ["vicinity"], "fire": ["reload"], "lunge": ["jump"], "polish": ["clean"], "man": ["dance", "email", "climb", "bicyclist", "racer", "mime", "stuntman", "city", "draw", "shirtless", "american", "pink", "skateboarder", "on", "in", "band", "smoking", "two", "pants", "play", "biker", "large", "down", "chef", "couple", "snowboard", "add", "electronic", "pianist", "potato", "musician", "sunglass", "climb", "bloke", "hiker", "magician", "singer", "cook", "frog", "girl", "eat", "into", "three", "kid", "podium", "bald", "young", "kitten", "ride", "against", "dog", "wetsuit", "player", "empty", "monkey", "standing", "fighting", "walking", "motorcyclist", "father", "four", "guitar", "cyclist", "lady", "orange", "stand", "camera", "dim", "make", "knife"], "indoor": ["in", "practice", "wall", "boy"], "railing": ["hill"], "bright": ["darkened"], "untie": ["climb"], "hang": ["run", "make", "stand"], "upside-down": ["idle", "dance"], "background": ["sand", "jacket", "mud"], "stone": ["fountain", "ground", "path"], "musician": ["man"], "beer": ["glass"], "kickbox": ["kickboxing"], "beat": ["stir"], "fervently": ["pray"], "cap": ["hat"], "spit": ["laugh"], "fearlessly": ["air", "waterskie", "wakeboard"], "revealing": ["red"], "step": ["staircase"], "tattered": ["broken"], "bite": ["drop", "out", "chase", "carry", "lick", "catch"], "device": ["telephone"], "box": ["use"], "indian": ["egyptian"], "lick": ["walk", "bite", "play"], "show": ["hold"], "extract": ["throw"], "come": ["climb"], "wrestle": ["attack"], "run": ["jump", "chase", "gather", "hold", "sit", "use", "emerge", "watch", "frolic", "up", "climb", "rest", "walk", "lie", "down", "stand", "stop", "fight", "perform", "drop"], "sound": ["white", "dance"], "frisbee": ["broken"], "climb": ["get", "ground", "city", "come", "untie", "play", "stand"], "liner": ["cosmetic"], "upside": ["crawl"], "ankle": ["woman"], "idle": ["upside-down", "play", "dance"], "for": ["at", "with", "out", "use", "operate", "uniform", "store", "on", "gear", "into", "scooter", "through", "in", "pour"], "mountainside": ["hill"], "with": ["write", "at", "into", "thick", "in", "wedding", "sit", "through", "inside", "over", "hard", "smile", "against", "play", "use", "squirt", "sign", "flute", "from", "fist", "suit", "white", "have", "child", "kid", "climb", "sewing", "set", "past", "water", "hand", "chair", "adult", "zucchini", "without", "hike", "throw", "wing", "cut", "eat", "on", "the", "little", "hold", "kick", "walk", "trick"], "harmlessly": ["fall"], "onto": ["off", "on", "in", "into"], "ground": ["stone", "wall", "brown", "hind"], "laugh": ["spit", "hold"], "rain": ["snow", "snowy"], "ring": ["fighting"], "eastern": ["kid", "man"], "surfboard": ["surfer"], "frame": ["air"], "word": ["talk"], "guide": ["map", "child"], "loudly": ["speak", "play"], "furiously": ["off", "full", "catch"], "shallow": ["milk"], "furious": ["horse"], "towards": ["hand", "through"], "sunset": ["camera", "through"], "capsicum": ["garlic"], "puke": ["eat"], "star": ["sky"], "keep": ["run", "next"], "top": ["metal", "on", "roof", "horse", "rock"], "discard": ["prepare"], "bamboo": ["man", "flute"], "shiny": ["blue"], "almost": ["street"], "animal": ["child"], "standing": ["dog", "walking"], "malnourished": ["healthy", "brown"], "laden": ["blanket"], "hay": ["cow"], "trek": ["hike"], "bring": ["run"], "pepper": ["garlic", "dice"], "graffitus": ["graphitize"], "breathlessly": ["carry", "run", "stand"], "counter": ["countertop"], "scrub": ["pack"], "toddler": ["boy"], "sit": ["practice", "run", "wear", "sunset", "jump", "lean", "seek", "perform", "wait", "outside", "play", "frolic", "wade", "look", "cluster", "speak", "side", "crawl", "black", "sing", "slide", "relax", "take"], "peel": ["refrigerate", "put", "eat", "banana"], "night": ["morning"], "still": ["play", "walk", "cover", "stand", "drink", "run", "water"], "stack": ["block"], "carefully": ["drive", "pack", "debon", "pour", "put", "wear", "feed", "walk", "prepare", "slice", "comb", "climb"], "dead": ["leafless"], "art": ["at"], "open": ["use", "play", "bite"], "put": ["pace", "peel", "pour", "slice", "garlic", "up", "walk", "sprinkle", "cut", "boil", "paint"], "completely": ["make"], "reload": ["fire", "shoot"], "potato": ["tomato", "carrot", "onion"], "asleep": ["experience"], "under": ["over", "from"], "burning": ["car"], "terrain": ["rocky"], "fur": ["bucket", "cat"], "alone": ["dance", "walk", "have"], "cover": ["slide", "still", "off", "over", "white"], "suite": ["bikini", "dune"], "get": ["squirt", "climb", "ride", "jump", "push", "perform"], "food": ["eat"], "mixture": ["egg", "meat"], "fight": ["two", "frolic", "inside", "practice", "lie", "play"], "couch": ["boy", "chair"], "across": ["through", "at", "wave", "along", "on", "cross", "in"], "rodeo": ["mechanical"], "suit": ["put", "into", "hat"], "large": ["dog", "steak", "flute", "cheerleader", "newspaper", "birdcage", "pattern", "cage", "white", "friend", "many", "purple", "brown"], "liquid": ["oil"], "happily": ["dance", "play", "slide", "talk", "sit"], "none": ["five"], "receive": ["serve"], "air": ["shirt", "fearlessly", "leotard", "in", "plane", "racing", "mouth", "man", "airborne", "snow", "water", "over"], "ledge": ["balcony"], "shake": ["empty"], "band": ["man"], "track": ["ramp", "motorcycle", "race"], "lady": ["girl", "boy", "tomato", "bikini", "man"], "emerge": ["run"], "internet": ["webcam"], "classroom": ["student"], "kickboxing": ["kickbox"], "flow": ["beautiful"], "delightedly": ["play"], "structure": ["with"], "intense": ["guitar", "intensely"], "at": ["through", "watch", "man", "talk", "to", "into", "away", "for", "across", "next", "around", "in", "with", "near", "sit", "water", "calendar", "on", "against", "eat", "play", "from"], "on": ["young", "counter", "podium", "horse", "orange", "top", "phone", "across", "woman", "man", "at", "from", "one", "devour", "onstage", "wave", "into", "piano", "about", "in", "for", "two", "do", "over", "of", "through", "down", "onto", "carrot", "near", "kitten", "butter"], "slow": ["race"], "cheer": ["crawl", "lower", "scare"], "cut": ["tear", "up", "plant", "add", "put"], "fetch": ["bite"], "immobile": ["swim", "swimming"], "tractor": ["tire"], "bathing": ["swim"], "part": ["around"], "relax": ["sit", "take"], "underwater": ["water"], "in": ["across", "on", "chasing", "from", "sing", "around", "cooking", "hike", "mid", "little", "drive", "other", "onto", "play", "tiny", "kid", "off", "child", "lone", "under", "inside", "through", "for", "white", "of", "ride", "sit", "hold", "into", "indoor", "defend", "up", "behind", "snow", "lion", "pants", "past", "corndog", "run", "outside", "smoking", "near", "man", "with", "rink", "girl", "teenage", "at", "boil", "down"], "perform": ["jump", "raise", "run", "sit", "powerfully", "get", "cheer", "full", "ride", "leave", "perch", "outdoors"], "leg": ["foot"], "helmeted": ["woman"], "lake": ["camera"], "dark": ["big", "sunglass"], "huge": ["small", "dye"], "comfortably": ["sit"], "ear": ["target", "headband", "midspeech"], "dog": ["two", "daschund", "large", "horse", "cat", "man"], "tofu": ["onion", "butter"], "pack": ["sheep", "scrub", "play"], "AccI": ["open", "speak", "play", "run", "do"], "playing": ["kid"], "wire": ["whisk"], "baby": ["boy", "bear", "panda", "splash", "cub"], "trip": ["two"], "soccer": ["ball", "outside", "on", "tennis", "with", "rugby"], "pyramid-shaped": ["bicycle"], "serve": ["receive"], "morning": ["night"], "lie": ["wear", "bounce", "play", "run", "outside", "hold"], "be": ["speak"], "official": ["player"], "differently": ["dress"], "the": ["man", "cat", "white"], "remove": ["put", "eat", "pour", "strongly"], "allow": ["play"], "bellbottom": ["pink", "boa"], "beach": ["ride", "park", "shore", "sandy", "seashore", "restaurant", "beside", "sand", "mountain", "sea", "wear", "bike"], "raft": ["boat"], "loud": ["man"], "only": ["do"], "shave": ["sharpen"], "yard": ["man", "court", "run"], "head": ["headdress", "nose", "flap"], "wooded": ["desert", "wood", "outdoor"], "scare": ["cheer"], "town": ["man"], "cook": ["place", "cut", "chop"], "plastic": ["cat", "mask", "toy", "drawer", "sword"], "bicycle": ["trick", "car", "gear"], "quiet": ["play"], "stare": ["stand", "jump", "study", "drop", "play", "grab"], "telephone": ["telephonic"], "various": ["large", "restaurant"], "snap": ["play"], "police": ["motorcycle"], "wedding": ["veil"], "dance": ["do", "sing", "challengingly", "play", "idle", "stand", "walk", "woman"], "same": ["costume", "forest"], "pink": ["ride", "on", "bunny", "dress", "with", "grassy", "rope", "orange"], "wear": ["sit", "fire", "bike", "happily", "color", "naked", "lean", "walk", "kick", "write", "shoot", "bare-chested", "take", "snow", "pose", "away", "run", "ride", "box", "open", "dance", "lie", "shirtless"], "ocean": ["together", "pool", "on"], "equipment": ["sound"], "paw": ["cat"], "daschund": ["dog", "cat"], "kiddie": ["paddling"], "race": ["ear", "wait", "jump", "swim", "rest", "play"], "smile": ["swim", "wear", "stand"], "map": ["guide", "signboard"], "shirt": ["man", "green", "shirtless", "air", "orange", "surfer", "leaf", "through", "front", "hand", "arm"], "right": ["ground"], "lead": ["escort"], "cart": ["man"], "tomato": ["potato", "bun"], "glove": ["boxing"], "full": ["listen", "small", "completely", "with", "blow", "lot", "play", "on", "wall", "motocross"], "tease": ["pull"], "paper": ["note"], "concrete": ["step"], "reveal": ["wear"], "snowboard": ["ski"], "protective": ["trainer", "protection"], "revive": ["help", "heal"], "photo": ["camera"], "gear": ["for", "rope", "goggles", "biker", "motocross", "swimsuit"], "makeup": ["striped", "face"], "tall": ["field", "grass", "set", "wall"], "of": ["bowl", "outside", "man", "woman", "rocky", "on", "dog", "open", "flute", "off", "toy", "over", "rope", "container", "in", "top", "into", "front", "door", "two", "lot", "through"], "flyaway": ["guitar"], "drink": ["spill"], "cat": ["white", "dog", "daschund", "kitten"], "eye": ["cosmetic"], "water": ["oil", "air", "boil", "squirt", "egg", "wave", "fountain", "beach"], "accident": ["motocross", "bike"], "read": ["play"], "type": ["operate"], "one": ["dog", "on", "two", "man"], "chubby": ["boy"], "athletically": ["jump"], "concentrated": ["woman"], "ceiling": ["floor", "fan"], "escape": ["rise", "come"], "wood": ["steel", "rope", "woman", "another", "door", "desert", "stick", "wooded"], "toy": ["plastic"], "swiftly": ["fly", "run", "down", "make", "dice"], "clove": ["capsicum", "pepper"], "carrot": ["potato", "onion", "chop"], "electronic": ["picture", "flute", "instrument"], "have": ["dig", "white", "color", "over", "rest", "lie", "in", "leap"], "wait": ["sit", "stand", "jump", "ride"], "mindlessly": ["slice"], "headband": ["ear"], "clean": ["yellow", "polish", "water", "prepare", "wipe", "erase"], "scooter": ["tricycle"], "pitifully": ["beg"], "marsh": ["river", "water"], "rock": ["city", "mountain", "cliff", "top"], "lot": ["fountain", "outdoors"], "piano": ["violin", "keyboard", "guitar", "wooden", "stage"], "down": ["sit", "around", "climb", "naked", "through", "stop", "show", "on", "dog", "cut", "run", "throw", "walk", "hold", "crowd", "lie", "crawl"], "sharp": ["corner"], "plant": ["dog"], "exciting": ["swing"], "trick": ["bicycle", "stunt", "bike", "soccer", "jump", "skateboard", "acrobatics"], "necklace": ["bead"], "fix": ["fit", "apply"], "clothing": ["woman"], "ski": ["snowboard"], "nude": ["topless"], "fall": ["off", "ride", "walk", "play"], "require": ["practice"], "wheel": ["atv", "motorcycle", "motorbike"], "crouch": ["show"], "uniform": ["band", "same", "white", "bmx", "muzzle"], "square": ["table", "small"], "via": ["with"], "roar": ["around"], "darkened": ["red", "bright", "room"], "porch": ["skateboard"], "outdoors": ["dog", "child", "karate", "lot", "playing", "park", "snow", "costume", "outdoor"], "construction": ["work"], "dirt": ["bmx", "two", "bike", "dog", "biker"], "knife": ["cut", "man", "pencil", "blade"], "tee": ["little"], "mechanical": ["rodeo"], "fence": ["large"], "paved": ["lead", "road"], "watch": ["stare", "stand", "away", "waterskie", "empty", "walk", "look", "play", "climb", "wear"], "preteen": ["boy"], "bird": ["birdcage", "beside"], "dive": ["ride"], "attentively": ["check", "funnily", "ignore", "look", "closely"], "side": ["break", "white", "left", "road", "fountain", "black", "ground", "dog"], "goal": ["goalkeeper"], "enthusiastically": ["play"], "stick": ["swing", "bite"], "mix": ["stir", "sound", "separate", "break"], "apply": ["fit", "pencil", "fix"], "mural": ["colorful"], "mid": ["in", "air", "mouth"], "cramped": ["crowded"], "intensely": ["play", "intense"], "tennis": ["ball", "outside", "pong", "soccer", "football"], "tug": ["duel"], "traffic": ["vehicle"], "shrewdly": ["shrewd", "burrow"], "basket": ["bucket"], "away": ["wear", "dice", "check", "look", "watch", "up", "perform", "peel", "slice", "hang", "stand", "lick", "cut", "coat", "take", "play", "chase"], "crawl": ["toddle", "slide", "sit"], "shun": ["follow"], "against": ["in", "near", "at", "with"], "speak": ["silent", "sit", "be", "tank"], "grand": ["stage"], "scratch": ["stroke"], "jersey": ["player"], "afghan": ["scarf"], "pattern": ["newspaper"], "bottle": ["water", "faucet"], "crowded": ["empty", "cramped", "city"], "rod": ["line"], "spotted": ["dog"], "fast": ["quickly", "eat"], "countertop": ["counter"], "spill": ["drink"], "mess": ["style"], "open-air": ["jeep"], "cyclone": ["low", "fence"], "kick": ["roll", "perform", "practice"], "tree": ["eat", "forest", "log", "target"], "pavement": ["hand"], "stove": ["into", "pot"], "light": ["tan", "darkened", "boy", "great", "lamp"], "tunnel": ["tube"], "sleep": ["walk", "roll", "look", "eat", "play"], "gallery": ["guide", "couple"], "hungry": ["woman", "eat"], "mouth": ["out", "with", "grass", "mid"], "closely": ["attentively"], "waterskie": ["wakeboard", "watch"], "heavily": ["wall"], "attack": ["wrestle"], "monkey": ["chimp", "man"], "colored": ["crocodile", "pool", "inflatable"], "stenography": ["stenograph"], "money": ["sign"], "wildly": ["climb", "play"], "barefoot": ["bicycle", "wear", "boy"], "rider": ["motocross", "biker", "horse", "friend", "bike"], "instrument": ["keyboard"], "stroke": ["scratch"], "bloke": ["guy"], "wetsuit": ["surfboard", "surf"], "empty": ["with", "crowded", "boot", "watch"], "ginger": ["onion"], "holiday": ["gift"], "trunk": ["bridge", "log"], "hold": ["run", "look", "show", "retrieve", "laugh", "ride", "climb", "watch", "slice", "do", "drop", "dance", "play", "laugh"], "seadoo": ["jetskus"], "airborne": ["dirt", "jump", "take", "air", "do"], "dash": ["jump"], "roll": ["sleep", "lay", "line"], "elder": ["elderly"], "biker": ["rider", "jumper", "boy", "bike", "mountain", "two", "man", "dirt"], "blue": ["gear", "green", "colorful", "walk", "with", "fly", "hike", "purple", "ball", "pool"], "spot": ["tan", "lie"], "chicken": ["oil", "cooking"], "can": ["jar"], "fun": ["slide"], "painting": ["man"], "furry": ["brown", "drop", "dog", "bite"], "pose": ["kneel", "look", "deny"], "study": ["look", "operate", "shred", "play", "stare"], "rough": ["dirt"], "note": ["paper"], "glass": ["sunglass", "bowl", "headdress", "beer", "hat"], "blade": ["knife", "man"], "mound": ["on"], "house": ["outside"], "singing": ["guitar"], "range": ["target"], "crack": ["place", "take", "talk", "add"], "droplet": ["water"], "garlic": ["slice", "sliced", "capsicum", "pepper", "onion", "chop"], "bun": ["tomato"], "cement": ["ledge"], "stop": ["do", "cross", "ride", "down"], "country": ["tree"], "pool": ["ocean"], "garden": ["outdoors", "lawn", "outside", "stone"], "hill": ["snow", "hillside", "mountainside", "beach", "through", "slide", "uphill", "still", "mountain", "railing", "into"], "fearfully": ["slowly", "walk"], "piece": ["precisely", "bike", "couch", "carrot", "dice"], "city": ["rock", "tower", "crowded", "street"], "playful": ["young"], "add": ["season", "crack", "remove", "season"], "dancing": ["man"], "post": ["pole"], "precisely": ["cut", "up"], "launch": ["toss"], "silently": ["perform"], "along": ["across", "man", "down", "dog"], "sprint": ["splash"], "together": ["sit", "run", "play", "hold", "stand", "play", "run"], "operate": ["type", "study"], "protection": ["practice", "protective"], "football": ["tennis", "fall"], "skinned": ["black"], "corner": ["red"], "oil": ["liquid"], "spray": ["play"], "(_knife": ["knife"], "inside": ["over"], "dig": ["have"], "wade": ["stand", "splash", "sit", "water"], "earring": ["bead"], "pen": ["lion", "rhino", "pasture"], "foot": ["leg"], "kitten": ["milk", "cat"], "outdoor": ["porch", "skateboard", "outdoors"], "puddle": ["mud"], "mantel": ["fireplace"], "cheerfully": ["look", "play", "wear", "around", "joyfully"], "march": ["band", "wear"], "meat": ["egg", "season"], "tackle": ["pole"], "bare": ["climb"], "investigate": ["look"], "separate": ["mix"], "vegetable": ["ingredient"], "knock": ["off", "push"], "teenage": ["girl"], "slide": ["sit", "snowboard", "cover", "still", "crawl"], "field": ["park", "grass", "outside", "practice", "white", "graze", "street", "green", "gym", "drive"], "circle": ["dance"], "occidental": ["oriental"], "unstitch": ["sew"], "boat": ["ship", "raft"], "homeless": ["man"], "surf": ["ocean", "play"], "cliff": ["rock"], "distant": ["walk", "hike"], "soup": ["bowl"], "draw": ["erase", "aim"], "striped": ["sand", "strip", "green"], "sunglass": ["guy", "glass", "bloke", "hair", "hand", "newspaper"], "cross": ["stop"], "really": ["eat", "long"], "cabinet": ["table"], "breed": ["dog", "striped"], "twin": ["two"], "sponsor": ["motocross"], "excitedly": ["snap", "fall"], "trampoline": ["into"], "curb": ["sidewalk"], "sand": ["beach", "shore", "camel", "grass", "golden"], "buttons": ["microwave"], "duel": ["tug"], "spout": ["watch"], "bend": ["drive"], "male": ["cheerleader"], "up": ["dice", "garlic", "in", "out", "hold", "fearful", "cut", "ride", "put", "climb", "investigate", "look", "sniff", "uphill", "jump", "slice", "make", "plant", "drop", "awaken", "run", "guy"], "small": ["pool", "two", "stage", "container", "flute", "hedgehog", "table", "statue", "very", "square", "foamy", "the", "bottle", "child", "ball", "package", "monkey", "guinea", "huge"], "three": ["white", "five", "woman", "rocky", "two", "child", "scooter", "teenage", "kid", "man"], "christmas": ["happy", "reindeer"], "metal": ["biker", "fence", "top"], "tray": ["eat"], "bead": ["black"], "road": ["man", "sidewalk", "lead", "path", "run", "grass", "lawn"], "patch": ["black"], "tan": ["black", "yellow", "red", "run", "dog"], "kid": ["dog", "man", "into", "swimmer"], "season": ["remove", "eat", "shredded", "pour", "put"], "silent": ["dance", "eat", "speak", "play", "talk"], "couple": ["man", "adult"], "drill": ["close"], "grotto": ["colorful"], "serious": ["laugh", "look"], "body": ["paint", "lake", "front", "water", "river"], "passionately": ["sing", "kiss", "play"], "strongly": ["remove", "make", "use", "beat"], "signboard": ["map"], "fallen": ["dead", "tree"], "military": ["officer"], "asian": ["brown", "elegant"], "near": ["biker", "from", "in", "against", "through", "on", "at"], "room": ["ceiling", "park", "keyboard"], "arrangement": ["area"], "wipe": ["spread", "remove", "clean"], "film": ["mostly"], "wooden": ["pole", "piano", "metallic", "window", "tile", "table", "five"], "day": ["on", "drink", "through", "man"], "cord": ["rope"], "jump": ["mid", "fly", "lunge", "get", "perform", "ski", "red", "race", "full", "run", "down", "stand", "catch", "dash", "wait", "do", "sit", "ride", "trick", "airborne", "rest", "flip", "play", "uniform"], "south": ["airplane"], "funny": ["face", "serious"], "low": ["rocky", "cyclone", "wall", "front"], "cub": ["baby", "tiger"], "friend": ["rider", "large"], "street": ["steep", "puddle", "map", "sidewalk", "field", "through", "walk"], "leather": ["boot", "with"], "cold": ["water"], "spar": ["kickbox", "do"], "repair": ["burn"], "slowly": ["peel", "fly", "walk", "add", "fearfully", "dance", "hike", "tiredly", "wake"], "fearful": ["up", "boy"], "picture": ["camera", "device"], "pan": ["cooking", "pot"], "hairy": ["man"], "lovely": ["flute"], "close": ["tree", "stand", "run", "drill", "roll", "wear", "play"], "pasta": ["sticky"], "guitar": ["trumpet", "tambourine", "harp", "flute", "drum", "keyboard", "piano"], "joyful": ["mountain"], "landscape": ["snow", "terrain"], "long": ["building", "blue"], "ruffle": ["little"], "tricycle": ["scooter"], "dirty": ["soccer", "dog", "very", "ball", "shirtless"], "olive": ["oil"], "aimlessly": ["pace", "walk", "sit"], "push": ["get", "turn", "knock"], "concert": ["singing", "woman"], "approach": ["drive", "through"], "gracefully": ["dance", "walk"], "(exists": ["with", "speak", "two"], "from": ["in", "ground", "into", "over", "under", "off", "near", "with", "come", "at", "on"], "bald": ["man"], "dyed": ["grey", "red", "ride", "yellow"], "kayake": ["man", "ride", "kayak"], "clothes": ["white"], "costume": ["bike", "karate", "mask"], "playground": ["outdoor"], "bride": ["girl", "woman"], "flute": ["piano", "guitar", "keyboard"], "electric": ["guitar", "bicycle"], "bunch": ["yellow", "man", "beach", "child"], "comfortable": ["table"], "donation": ["case"], "attend": ["watch"], "swing": ["ball", "little"], "mud": ["puddle", "man"], "clumsily": ["put", "kick", "swim", "hold", "man"], "splash": ["wade", "play", "run", "sprint"], "racing": ["rally", "racer"], "rainy": ["sunny", "bench"], "log": ["tree"], "check": ["throw"], "scatter": ["group", "herd"], "bear": ["baby"], "strum": ["play"], "topless": ["laugh", "clear", "nude", "woman"], "hair": ["manicure", "chair", "arm", "bottle", "guitar", "blond"], "wrap": ["cut"], "size": ["newspaper", "pattern"], "erase": ["clean"], "bull": ["dog"], "park": ["gym", "play", "bench", "ride", "front", "skater", "skateboard", "beach", "room"], "guy": ["boy", "bloke"], "pull": ["tease"], "skyline": ["biker"], "hat": ["camera", "bikini", "tongue", "still", "cap", "man", "blue"], "upward": ["brown"], "thick": ["beautiful", "rope"], "faucet": ["bottle", "container"], "acrobatics": ["trick", "airborne", "on"], "wheelie": ["motorcycle", "wheel"], "court": ["yard"], "oriental": ["girl", "woman", "occidental", "camera"], "seashore": ["sidewalk", "beach"], "fly": ["perch", "swiftly", "ball"], "gnaw": ["eat", "devour"]}